Metadata-Version: 1.1
Name: nested-h5py
Version: 0.0.2
Summary: Pandas reader and writer from h5py
Home-page: https://github.com/neuroneuro15/nested_h5py
Author: Nicholas A. Del Grosso
Author-email: delgrosso.nick@gmail.com
License: BSD
Download-URL: https://github.com/neuroneuro15/nested_h5py/tarball/0.0.2
Platform: UNKNOWN
Classifier: Development Status :: 3 - Alpha
Classifier: Intended Audience :: Developers
Classifier: Programming Language :: Python :: 3
Classifier: Programming Language :: Python :: 2
